Digital_Systems/labs/experiments/projects/experiment4/8_1Mux_mux/src/mux8_1.vhdl
library IEEE;
use IEEE.STD_LOGIC_1164.ALL;

entity mux8_1 is
port(
	A,B,C,D,E,F,G,H : in STD_LOGIC;
	S2,S1,S0: in STD_LOGIC;
	Z1: out STD_LOGIC
);
end mux8_1;

architecture smsa of mux8_1 is
component mux2_1
port(
	A,B:in STD_LOGIC;
	S2: in STD_LOGIC;
	Z: out STD_LOGIC
);
end component;

component mux4_1
port(
	A,B,C,D : in STD_LOGIC;
	S0,S1: in STD_LOGIC;
	Z: out STD_LOGIC
);
end component;

signal temp1, temp2: std_logic;
begin
	m1: mux4_1 port map(A,B,C,D,S0,S1,temp1);
	m2: mux4_1 port map(E,F,G,H,S0,S1,temp2);
	m3: mux2_1 port map(temp1,temp2,S2,Z1);

end smsa;


library IEEE;
use IEEE.STD_LOGIC_1164.ALL;

entity mux4_1 is
port(
    A,B,C,D : in STD_LOGIC;
    S0,S1 : in STD_LOGIC;
    Z : out STD_LOGIC
);
end mux4_1;

architecture sms of mux4_1 is
begin
	process (A,B,C,D,S0,S1) is
	begin
		  if (S0 ='0' and S1 = '0') then
		      Z <= A;
		  elsif (S0 ='1' and S1 = '0') then
		      Z <= B;
		  elsif (S0 ='0' and S1 = '1') then
		      Z <= C;
		  else
		      Z <= D;
	      end if;
	end process;
end sms;


library IEEE;
use IEEE.STD_LOGIC_1164.ALL;

entity mux2_1 is
port(
	A,B:in STD_LOGIC;
	S2:in STD_LOGIC;
	Z:out STD_LOGIC
);
end mux2_1;

architecture sms of mux2_1 is
begin
 with S2 select
	Z<= A when '0',
	B when others;
end sms;

Digital_Systems/labs/experiments/projects/experiment4/8_1Mux_mux/testbench/tb_mux.vhdl
LIBRARY ieee;
USE ieee.std_logic_1164.ALL;

ENTITY tb_mux IS
END tb_mux;

ARCHITECTURE behavior OF tb_mux IS

    COMPONENT mux8_1
    PORT(
	A,B,C,D,E,F,G,H : in STD_LOGIC;
	S2,S1,S0: in STD_LOGIC;
	Z1: out STD_LOGIC
        );
    END COMPONENT;

   signal A : std_logic := '0';
   signal B : std_logic := '0';
   signal C : std_logic := '0';
   signal D : std_logic := '0';
   signal E : std_logic := '0';
   signal F : std_logic := '0';
   signal G : std_logic := '0';
   signal H : std_logic := '0';
   signal S0 : std_logic := '0';
   signal S1 : std_logic := '0';
   signal S2 : std_logic := '0';
 	--Outputs
   signal Z1 : std_logic;

BEGIN
   uut: mux8_1 PORT MAP (
         A => A,
         B => B,
         C => C,
	 D => D,
         E => E,
         F => F,
         G => G,
         H => H,
         S0 => S0,
         S1 => S1,
         S2 => S2,
         Z1 => Z1
        );

   stim_proc: process
   begin
      wait for 100 ns;
	A <= '1';
	B <= '0';
	C <= '1';
	D <= '0';
	E <= '1';
	F <= '0';
	G <= '1';
	H <= '0';

	S0 <= '0'; S1 <= '0'; S2 <= '0';
		wait for 100 ns;
	S0 <= '1'; S1 <= '0'; S2 <= '0';
		wait for 100 ns;
	S0 <= '0'; S1 <= '1'; S2 <= '0';
		wait for 100 ns;
	S0 <= '1'; S1 <= '1'; S2 <= '0';
		wait for 100 ns;
	S0 <= '0'; S1 <= '0'; S2 <= '1';
	        wait for 100 ns;
	S0 <= '1'; S1 <= '0'; S2 <= '1';
	        wait for 100 ns;
	S0 <= '0'; S1 <= '1'; S2 <= '1';
		wait for 100 ns;
	S0 <= '1'; S1 <= '1'; S2 <= '1';
		wait for 100 ns;
	end process;
END;

Digital_Systems/labs/experiments/projects/experiment4/8_1Mux_mux/simulation/tb_mux.vcd
$date
  Sat Sep 19 19:17:44 2020
$end
$version
  GHDL v0
$end
$timescale
  1 fs
$end
$scope module standard $end
$upscope $end
$scope module std_logic_1164 $end
$upscope $end
$scope module tb_mux $end
$var reg 1 ! a $end
$var reg 1 " b $end
$var reg 1 # c $end
$var reg 1 $ d $end
$var reg 1 % e $end
$var reg 1 & f $end
$var reg 1 ' g $end
$var reg 1 ( h $end
$var reg 1 ) s0 $end
$var reg 1 * s1 $end
$var reg 1 + s2 $end
$var reg 1 , z1 $end
$scope module uut $end
$var reg 1 - a $end
$var reg 1 . b $end
$var reg 1 / c $end
$var reg 1 0 d $end
$var reg 1 1 e $end
$var reg 1 2 f $end
$var reg 1 3 g $end
$var reg 1 4 h $end
$var reg 1 5 s2 $end
$var reg 1 6 s1 $end
$var reg 1 7 s0 $end
$var reg 1 8 z1 $end
$var reg 1 9 temp1 $end
$var reg 1 : temp2 $end
$scope module m1 $end
$var reg 1 ; a $end
$var reg 1 < b $end
$var reg 1 = c $end
$var reg 1 > d $end
$var reg 1 ? s0 $end
$var reg 1 @ s1 $end
$var reg 1 A z $end
$upscope $end
$scope module m2 $end
$var reg 1 B a $end
$var reg 1 C b $end
$var reg 1 D c $end
$var reg 1 E d $end
$var reg 1 F s0 $end
$var reg 1 G s1 $end
$var reg 1 H z $end
$upscope $end
$scope module m3 $end
$var reg 1 I a $end
$var reg 1 J b $end
$var reg 1 K s2 $end
$var reg 1 L z $end
$upscope $end
$upscope $end
$upscope $end
$enddefinitions $end
#0
0!
0"
0#
0$
0%
0&
0'
0(
0)
0*
0+
0,
0-
0.
0/
00
01
02
03
04
05
06
07
08
09
0:
0;
0<
0=
0>
0?
0@
0A
0B
0C
0D
0E
0F
0G
0H
0I
0J
0K
0L
#100000000
1!
1#
1%
1'
1,
1-
1/
11
13
18
19
1:
1;
1=
1A
1B
1D
1H
1I
1J
1L
#200000000
1)
0,
17
08
09
0:
1?
0A
1F
0H
0I
0J
0L
#300000000
0)
1*
1,
16
07
18
19
1:
0?
1@
1A
0F
1G
1H
1I
1J
1L
#400000000
1)
0,
17
08
09
0:
1?
0A
1F
0H
0I
0J
0L
#500000000
0)
0*
1+
1,
15
06
07
18
19
1:
0?
0@
1A
0F
0G
1H
1I
1J
1K
1L
#600000000
1)
0,
17
08
09
0:
1?
0A
1F
0H
0I
0J
0L
#700000000
0)
1*
1,
16
07
18
19
1:
0?
1@
1A
0F
1G
1H
1I
1J
1L
#800000000
1)
0,
17
08
09
0:
1?
0A
1F
0H
0I
0J
0L
