Digital_Systems/labs/experiments/projects/experiment2/full_adder/nand_gate/src/adder.vhdl
library ieee;
use ieee.std_logic_1164.all;

entity full_adder is
    port (
        a  : in  std_logic;
        b  : in  std_logic;
        ci : in  std_logic;
        s  : out std_logic;
        co : out std_logic);
end;

architecture ADDER of full_adder is
	 signal w_WIRE_1 : std_logic;
	 signal w_WIRE_2 : std_logic;
	 signal w_WIRE_3 : std_logic;
	 signal w_WIRE_4 : std_logic;
	 signal w_WIRE_5 : std_logic;
	 signal w_WIRE_6 : std_logic;
	 signal w_WIRE_7 : std_logic;
begin
	w_WIRE_1 <= a nand b;
	w_WIRE_2 <= w_WIRE_1 nand a;
	w_WIRE_3 <= w_WIRE_1 nand b;
	w_WIRE_4 <= w_WIRE_2 nand w_WIRE_3;
	w_WIRE_5 <= w_WIRE_4 nand ci;
	w_WIRE_6 <= w_WIRE_5 nand w_WIRE_4;
	w_WIRE_7 <= w_WIRE_5 nand ci;

	s <= w_WIRE_6 nand w_WIRE_7;
	co <= w_WIRE_1 nand w_WIRE_5;
end;

Digital_Systems/labs/experiments/projects/experiment2/full_adder/nor_gate/testbench/adder_tb.vhdl
library ieee;
use ieee.std_logic_1164.all;

entity adder_tb is
end adder_tb;

architecture behavior of adder_tb is
    component full_adder is
        port (
            a  : in  std_logic;
            b  : in  std_logic;
            ci : in  std_logic;
            s  : out std_logic;
            co : out std_logic);
    end component;
    signal input  : std_logic_vector(2 downto 0);
    signal output : std_logic_vector(1 downto 0);
begin
    uut: full_adder port map (
        a => input(2),
        b => input(1),
        ci => input(0),
        s => output(0),
        co => output(1)
    );

    stim_proc: process
    begin
        input <= "000"; wait for 10 ns; assert output = "00" report "0+0+0 failed";
        input <= "001"; wait for 10 ns; assert output = "01" report "0+0+1 failed";
        input <= "010"; wait for 10 ns; assert output = "01" report "0+1+0 failed";
        input <= "011"; wait for 10 ns; assert output = "10" report "0+1+1 failed";
        input <= "100"; wait for 10 ns; assert output = "01" report "1+0+0 failed";
        input <= "101"; wait for 10 ns; assert output = "10" report "1+0+1 failed";
        input <= "110"; wait for 10 ns; assert output = "10" report "1+1+0 failed";
        input <= "111"; wait for 10 ns; assert output = "11" report "1+1+1 failed";
        report "Full adder testbench finished";
        wait;
    end process;
end;

Digital_Systems/labs/experiments/projects/experiment2/full_adder/nand_gate/simulation/adder_tb.vcd
$date
  Sat Aug  8 20:54:10 2020
$end
$version
  GHDL v0
$end
$timescale
  1 fs
$end
$scope module standard $end
$upscope $end
$scope module std_logic_1164 $end
$upscope $end
$scope module adder_tb $end
$var reg 3 ! input[2:0] $end
$var reg 2 " output[1:0] $end
$scope module uut $end
$var reg 1 # a $end
$var reg 1 $ b $end
$var reg 1 % ci $end
$var reg 1 & s $end
$var reg 1 ' co $end
$var reg 1 ( w_wire_1 $end
$var reg 1 ) w_wire_2 $end
$var reg 1 * w_wire_3 $end
$var reg 1 + w_wire_4 $end
$var reg 1 , w_wire_5 $end
$var reg 1 - w_wire_6 $end
$var reg 1 . w_wire_7 $end
$upscope $end
$upscope $end
$enddefinitions $end
#0
b000 !
b00 "
0#
0$
0%
0&
0'
1(
1)
1*
0+
1,
1-
1.
#10000000
b001 !
b01 "
1%
1&
0.
#20000000
b010 !
b01 "
1$
0%
1&
0*
1+
0-
1.
#30000000
b011 !
b10 "
1%
0&
1'
0,
1-
1.
#40000000
b100 !
b01 "
1#
0$
0%
1&
0'
0)
1*
1,
0-
#50000000
b101 !
b10 "
1%
0&
1'
0,
1-
1.
#60000000
b110 !
b10 "
1$
0%
0&
0(
1)
1*
0+
1,
1-
#70000000
b111 !
b11 "
1%
1&
0.
