Digital_Systems/labs/experiments/projects/experiment4/full_adder/src/fulladder.vhdl
library IEEE;
use IEEE.STD_LOGIC_1164.ALL;

entity fulladder is
port(
A : in STD_LOGIC;
B: in STD_LOGIC;
C: in STD_LOGIC;
S:out STD_LOGIC;
CA: out STD_LOGIC
);
end fulladder;

architecture smsb of fulladder is
component orgate
port( A,B:in STD_LOGIC;
Z: out STD_LOGIC);
end component;

component half_adder
port( a : in STD_LOGIC;
b: in STD_LOGIC;
sum:out STD_LOGIC;
carry: out STD_LOGIC);
end component;

signal sum1,carry1,carry2: std_logic;
begin
m1: half_adder port map(A,B,sum1,carry1);
m2: half_adder port map(C,sum1,S,carry2);
m3: orgate port map(carry1,carry2,CA);

end smsb;


library IEEE;
use IEEE.STD_LOGIC_1164.ALL;
entity half_adder is
   port(a,b:in STD_LOGIC; sum,carry:out STD_LOGIC);
end half_adder;

architecture halfadder of half_adder is
begin
   sum<= a xor b;
   carry <= a and b;
end halfadder;

library IEEE;
use IEEE.STD_LOGIC_1164.ALL;

entity orgate is
port(A,B:in STD_LOGIC;
Z : out STD_LOGIC);
end orgate;

architecture sms of orgate is
begin
	Z <= A or B;
end sms;

Digital_Systems/labs/experiments/projects/experiment4/full_adder/testbench/adder_tb.vhdl
library ieee;
use ieee.std_logic_1164.all;

entity adder_tb is
end adder_tb;

architecture behavior of adder_tb is
    component fulladder is
        port (
            A  : in  std_logic;
            B  : in  std_logic;
            C : in  std_logic;
            S  : out std_logic;
            CA : out std_logic);
    end component;
    signal input  : std_logic_vector(2 downto 0);
    signal output : std_logic_vector(1 downto 0);
begin
    uut: fulladder port map (
        A => input(2),
        B => input(1),
        C => input(0),
        S => output(0),
        CA => output(1)
    );

    stim_proc: process
    begin
        input <= "000"; wait for 10 ns; assert output = "00" report "0+0+0 failed";
        input <= "001"; wait for 10 ns; assert output = "01" report "0+0+1 failed";
        input <= "010"; wait for 10 ns; assert output = "01" report "0+1+0 failed";
        input <= "011"; wait for 10 ns; assert output = "10" report "0+1+1 failed";
        input <= "100"; wait for 10 ns; assert output = "01" report "1+0+0 failed";
        input <= "101"; wait for 10 ns; assert output = "10" report "1+0+1 failed";
        input <= "110"; wait for 10 ns; assert output = "10" report "1+1+0 failed";
        input <= "111"; wait for 10 ns; assert output = "11" report "1+1+1 failed";
        report "Full adder testbench finished";
        wait;
    end process;
end;

Digital_Systems/labs/experiments/projects/experiment4/full_adder/simulation/adder_tb.vcd
$date
  Sat Sep 19 22:17:33 2020
$end
$version
  GHDL v0
$end
$timescale
  1 fs
$end
$scope module standard $end
$upscope $end
$scope module std_logic_1164 $end
$upscope $end
$scope module adder_tb $end
$var reg 3 ! input[2:0] $end
$var reg 2 " output[1:0] $end
$scope module uut $end
$var reg 1 # a $end
$var reg 1 $ b $end
$var reg 1 % c $end
$var reg 1 & s $end
$var reg 1 ' ca $end
$var reg 1 ( sum1 $end
$var reg 1 ) carry1 $end
$var reg 1 * carry2 $end
$scope module m1 $end
$var reg 1 + a $end
$var reg 1 , b $end
$var reg 1 - sum $end
$var reg 1 . carry $end
$upscope $end
$scope module m2 $end
$var reg 1 / a $end
$var reg 1 0 b $end
$var reg 1 1 sum $end
$var reg 1 2 carry $end
$upscope $end
$scope module m3 $end
$var reg 1 3 a $end
$var reg 1 4 b $end
$var reg 1 5 z $end
$upscope $end
$upscope $end
$upscope $end
$enddefinitions $end
#0
b000 !
b00 "
0#
0$
0%
0&
0'
0(
0)
0*
0+
0,
0-
0.
0/
00
01
02
03
04
05
#10000000
b001 !
b01 "
1%
1&
1/
11
#20000000
b010 !
b01 "
1$
0%
1&
1(
1,
1-
0/
10
11
#30000000
b011 !
b10 "
1%
0&
1'
1*
1/
01
12
14
15
#40000000
b100 !
b01 "
1#
0$
0%
1&
0'
0*
1+
0,
0/
11
02
04
05
#50000000
b101 !
b10 "
1%
0&
1'
1*
1/
01
12
14
15
#60000000
b110 !
b10 "
1$
0%
0&
0(
1)
0*
1,
0-
1.
0/
00
01
02
13
04
#70000000
b111 !
b11 "
1%
1&
1/
11
