Digital_Systems/labs/experiments/projects/experiment5/gray_2_bin/dataflow/src/gray2bin.vhdl
library ieee;
use ieee.std_logic_1164.all;

entity gray2bin is
port(g: in std_logic_vector (3 downto 0);
     b: out std_logic_vector (3 downto 0));
end gray2bin;

architecture arch_gray2bin of gray2bin is
begin
	b(3) <= g(3);
	b(2) <= g(3) xor g(2);
	b(1) <= g(3) xor g(2) xor g(1);
	b(0) <= g(3) xor g(2) xor g(1) xor g(0);
end arch_gray2bin;

Digital_Systems/labs/experiments/projects/experiment5/gray_2_bin/dataflow/testbench/tb_bin.vhdl
library ieee;
use ieee.std_logic_1164.all;

entity tb_bin is
end tb_bin;

architecture behav of tb_bin is
	component gray2bin is
		port(g: in std_logic_vector (3 downto 0);
		     b: out std_logic_vector (3 downto 0)
	     );
	end component;

	signal input : std_logic_vector (3 downto 0);
	signal output: std_logic_vector (3 downto 0);
begin
	uut: gray2bin port map(
		g => input,
		b => output);
	stim_proc: process
	begin
		input <= "0000"; wait for 100 ns;
		input <= "0001"; wait for 100 ns;
		input <= "0010"; wait for 100 ns;
		input <= "0011"; wait for 100 ns;
		input <= "0100"; wait for 100 ns;
		input <= "0101"; wait for 100 ns;
		input <= "0110"; wait for 100 ns;
		input <= "0111"; wait for 100 ns;
		input <= "1000"; wait for 100 ns;
		input <= "1001"; wait for 100 ns;
		input <= "1010"; wait for 100 ns;
		input <= "1011"; wait for 100 ns;
		input <= "1100"; wait for 100 ns;
		input <= "1101"; wait for 100 ns;
		input <= "1110"; wait for 100 ns;
		input <= "1111"; wait for 100 ns;
		wait;
	end process;
end;

Digital_Systems/labs/experiments/projects/experiment5/gray_2_bin/dataflow/simulation/tb_bin.vcd
$date
  Sun Sep 20 12:42:05 2020
$end
$version
  GHDL v0
$end
$timescale
  1 fs
$end
$scope module standard $end
$upscope $end
$scope module std_logic_1164 $end
$upscope $end
$scope module tb_bin $end
$var reg 4 ! input[3:0] $end
$var reg 4 " output[3:0] $end
$scope module uut $end
$var reg 4 # g[3:0] $end
$var reg 4 $ b[3:0] $end
$upscope $end
$upscope $end
$enddefinitions $end
#0
b0000 !
b0000 "
b0000 #
b0000 $
#100000000
b0001 !
b0001 "
b0001 #
b0001 $
#200000000
b0010 !
b0011 "
b0010 #
b0011 $
#300000000
b0011 !
b0010 "
b0011 #
b0010 $
#400000000
b0100 !
b0111 "
b0100 #
b0111 $
#500000000
b0101 !
b0110 "
b0101 #
b0110 $
#600000000
b0110 !
b0100 "
b0110 #
b0100 $
#700000000
b0111 !
b0101 "
b0111 #
b0101 $
#800000000
b1000 !
b1111 "
b1000 #
b1111 $
#900000000
b1001 !
b1110 "
b1001 #
b1110 $
#1000000000
b1010 !
b1100 "
b1010 #
b1100 $
#1100000000
b1011 !
b1101 "
b1011 #
b1101 $
#1200000000
b1100 !
b1000 "
b1100 #
b1000 $
#1300000000
b1101 !
b1001 "
b1101 #
b1001 $
#1400000000
b1110 !
b1011 "
b1110 #
b1011 $
#1500000000
b1111 !
b1010 "
b1111 #
b1010 $
