Digital_Systems/labs/experiments/projects/experiment3/decoder/src/decoder.vhdl
library ieee;
use ieee.std_logic_1164.all;
entity decoder is
port(
	i0,i1,i2,E: in std_logic;
	d : out STD_LOGIC_VECTOR (7 downto 0));
end decoder;

architecture decod of decoder is
begin
	d(0)<=(not i0) and (not i1) and (not i2) and E;
	d(1)<=(not i0) and (not i1) and i2 and E;
	d(2)<=(not i0) and i1 and (not i2) and E;
	d(3)<=(not i0) and i1 and i2 and E;
	d(4)<=i0 and (not i1) and (not i2) and E;
	d(5)<=i0 and (not i1) and i2 and E;
	d(6)<=i0 and i1 and (not i2) and E;
	d(7)<=i0 and i1 and i2 and E;
end decod;

Digital_Systems/labs/experiments/projects/experiment3/decoder/testbench/tb_decoder.vhdl
library IEEE;
use IEEE.STD_LOGIC_1164.ALL;

entity tb_decoder is
end entity;

architecture tb of tb_decoder is
	component decoder is
		Port (
		i0: in STD_LOGIC;
		i1: in STD_LOGIC;
		i2: in STD_LOGIC;
		E : in STD_LOGIC;
		d : out STD_LOGIC_VECTOR (7 downto 0));
	end component;
	signal input: std_logic_vector(3 downto 0);
	signal d : STD_LOGIC_VECTOR (7 downto 0);

begin
	uut: decoder port map(
		i0 =>input(3),
		i1 =>input(2),
		i2 =>input(1),
		E  =>input(0),
		d  => d

	);

	stim: process
		begin
			input <= "---0"; wait for 10 ns;
		        input <= "0001"; wait for 10 ns;
			input <= "0011"; wait for 10 ns;
			input <= "0101"; wait for 10 ns;
			input <= "0111"; wait for 10 ns;
			input <= "1001"; wait for 10 ns;
			input <= "1011"; wait for 10 ns;
			input <= "1101"; wait for 10 ns;
			input <= "1111"; wait for 10 ns;

		wait;

end process;
end tb;

Digital_Systems/labs/experiments/projects/experiment3/decoder/simulation/tb_decoder.vcd
$date
  Mon Sep 14 11:33:36 2020
$end
$version
  GHDL v0
$end
$timescale
  1 fs
$end
$scope module standard $end
$upscope $end
$scope module std_logic_1164 $end
$upscope $end
$scope module tb_decoder $end
$var reg 4 ! input[3:0] $end
$var reg 8 " d[7:0] $end
$scope module uut $end
$var reg 1 # i0 $end
$var reg 1 $ i1 $end
$var reg 1 % i2 $end
$var reg 1 & e $end
$var reg 8 ' d[7:0] $end
$upscope $end
$upscope $end
$enddefinitions $end
#0
b---0 !
b00000000 "
-#
-$
-%
0&
b00000000 '
#10000000
b0001 !
b00000001 "
0#
0$
0%
1&
b00000001 '
#20000000
b0011 !
b00000010 "
1%
b00000010 '
#30000000
b0101 !
b00000100 "
1$
0%
b00000100 '
#40000000
b0111 !
b00001000 "
1%
b00001000 '
#50000000
b1001 !
b00010000 "
1#
0$
0%
b00010000 '
#60000000
b1011 !
b00100000 "
1%
b00100000 '
#70000000
b1101 !
b01000000 "
1$
0%
b01000000 '
#80000000
b1111 !
b10000000 "
1%
b10000000 '
