Digital_Systems/labs/experiments/projects/experiment5/bin_2_gray/behav/src/bin2gray_behav.vhdl
library ieee;
use ieee.std_logic_1164.all;

entity bin2gray_behav is
port(b: in bit_vector (3 downto 0);
     y: out bit_vector (3 downto 0));
end bin2gray_behav;

architecture arch_bin2gray_behav of bin2gray_behav is
begin

process(b)
  begin

    y(3) <= b(3);
    for i in 3 downto 1 loop

	      if ( b(i) = b(i-1)) then y(i-1) <= '0';
	      elsif ( b(i) /= b(i-1)) then y(i-1) <= '1';
	      end if;
	end loop;
      end process;

end arch_bin2gray_behav;

Digital_Systems/labs/experiments/projects/experiment5/bin_2_gray/behav/testbench/tb_gray.vhdl
library ieee;
use ieee.std_logic_1164.all;

entity tb_gray is
end tb_gray;

architecture behav of tb_gray is
	component bin2gray_behav is
		port(b: in bit_vector (3 downto 0);
		     y: out bit_vector (3 downto 0)
	     );
	end component;

	signal input : bit_vector (3 downto 0);
	signal output: bit_vector (3 downto 0);
begin
	uut: bin2gray_behav port map(
		b => input,
		y => output);
	stim_proc: process
	begin
		input <= "0000"; wait for 100 ns;
		input <= "0001"; wait for 100 ns;
		input <= "0010"; wait for 100 ns;
		input <= "0011"; wait for 100 ns;
		input <= "0100"; wait for 100 ns;
		input <= "0101"; wait for 100 ns;
		input <= "0110"; wait for 100 ns;
		input <= "0111"; wait for 100 ns;
		input <= "1000"; wait for 100 ns;
		input <= "1001"; wait for 100 ns;
		input <= "1010"; wait for 100 ns;
		input <= "1011"; wait for 100 ns;
		input <= "1100"; wait for 100 ns;
		input <= "1101"; wait for 100 ns;
		input <= "1110"; wait for 100 ns;
		input <= "1111"; wait for 100 ns;
		wait;
	end process;
end;

Digital_Systems/labs/experiments/projects/experiment5/bin_2_gray/behav/simulation/tb_gray.vcd
$date
  Sun Sep 20 12:41:27 2020
$end
$version
  GHDL v0
$end
$timescale
  1 fs
$end
$scope module standard $end
$upscope $end
$scope module std_logic_1164 $end
$upscope $end
$scope module tb_gray $end
$var reg 4 ! input[3:0] $end
$var reg 4 " output[3:0] $end
$scope module uut $end
$var reg 4 # b[3:0] $end
$var reg 4 $ y[3:0] $end
$upscope $end
$upscope $end
$enddefinitions $end
#0
b0000 !
b0000 "
b0000 #
b0000 $
#100000000
b0001 !
b0001 "
b0001 #
b0001 $
#200000000
b0010 !
b0011 "
b0010 #
b0011 $
#300000000
b0011 !
b0010 "
b0011 #
b0010 $
#400000000
b0100 !
b0110 "
b0100 #
b0110 $
#500000000
b0101 !
b0111 "
b0101 #
b0111 $
#600000000
b0110 !
b0101 "
b0110 #
b0101 $
#700000000
b0111 !
b0100 "
b0111 #
b0100 $
#800000000
b1000 !
b1100 "
b1000 #
b1100 $
#900000000
b1001 !
b1101 "
b1001 #
b1101 $
#1000000000
b1010 !
b1111 "
b1010 #
b1111 $
#1100000000
b1011 !
b1110 "
b1011 #
b1110 $
#1200000000
b1100 !
b1010 "
b1100 #
b1010 $
#1300000000
b1101 !
b1011 "
b1101 #
b1011 $
#1400000000
b1110 !
b1001 "
b1110 #
b1001 $
#1500000000
b1111 !
b1000 "
b1111 #
b1000 $
