Digital_Systems/labs/experiments/projects/bhavesh2/src/LFSR8.vhdl
LIBRARY ieee;
USE ieee.std_logic_1164.ALL;

ENTITY LFSR8 IS
  PORT (Clk, Rst: IN std_logic;
        output: OUT std_logic_vector (7 DOWNTO 0));
END LFSR8;

ARCHITECTURE LFSR8_beh OF LFSR8 IS
  SIGNAL Currstate, Nextstate: std_logic_vector (7 DOWNTO 0);
  SIGNAL feedback: std_logic;
BEGIN

  StateReg: PROCESS (Clk,Rst)
  BEGIN
    IF (Rst = '1') THEN
      Currstate <= (0 => '1', OTHERS =>'0');
    ELSIF (Clk = '1' AND Clk'EVENT) THEN
      Currstate <= Nextstate;
    END IF;
  END PROCESS;

  feedback <= Currstate(4) XOR Currstate(3) XOR Currstate(2) XOR Currstate(0);
  Nextstate <= feedback & Currstate(7 DOWNTO 1);
  output <= Currstate;

END LFSR8_beh;

Digital_Systems/labs/experiments/projects/bhavesh2/testbench/lsfr_test.vhdl
LIBRARY ieee;
USE ieee.std_logic_1164.ALL;

ENTITY lsfr_test IS
END lsfr_test;

ARCHITECTURE TBarch OF lsfr_test IS
  COMPONENT LFSR8 IS
    PORT (Clk, Rst: IN std_logic;
          output: OUT std_logic_vector (7 DOWNTO 0));
  END COMPONENT;

  SIGNAL Clk_s, Rst_s: std_logic;
  SIGNAL output_s: std_logic_vector(7 DOWNTO 0);

BEGIN
  CompToTest: LFSR8 PORT MAP (Clk_s, Rst_s, output_s);

  Clk_proc: PROCESS
  BEGIN
    Clk_s <= '1';
    WAIT FOR 10 ns;
    Clk_s <= '0';
    WAIT FOR 10 ns;
  END PROCESS clk_proc;

  Vector_proc: PROCESS
  BEGIN
    Rst_s <= '1';
    WAIT FOR 5 NS;
    Rst_s <= '0';
    FOR index IN 0 To 4 LOOP
      WAIT UNTIL Clk_s='1' AND Clk_s'EVENT;
    END LOOP;
    WAIT FOR 5 NS;
    ASSERT output_s = X"88" REPORT "Failed output=88";
    WAIT;
  END PROCESS Vector_proc;

END TBarch;

Digital_Systems/labs/experiments/projects/bhavesh2/simulation/lsfr_test.vcd
$date
  Sun Dec 20 12:28:09 2020
$end
$version
  GHDL v0
$end
$timescale
  1 fs
$end
$scope module standard $end
$upscope $end
$scope module std_logic_1164 $end
$upscope $end
$scope module lsfr_test $end
$var reg 1 ! clk_s $end
$var reg 1 " rst_s $end
$var reg 8 # output_s[7:0] $end
$scope module comptotest $end
$var reg 1 $ clk $end
$var reg 1 % rst $end
$var reg 8 & output[7:0] $end
$var reg 8 ' currstate[7:0] $end
$var reg 8 ( nextstate[7:0] $end
$var reg 1 ) feedback $end
$upscope $end
$upscope $end
$enddefinitions $end
#0
1!
1"
b00000001 #
1$
1%
b00000001 &
b00000001 '
b10000000 (
1)
#5000000
0"
0%
#10000000
0!
0$
#20000000
1!
b10000000 #
1$
b10000000 &
b10000000 '
b01000000 (
0)
#30000000
0!
0$
#40000000
1!
b01000000 #
1$
b01000000 &
b01000000 '
b00100000 (
#50000000
0!
0$
#60000000
1!
b00100000 #
1$
b00100000 &
b00100000 '
b00010000 (
#70000000
0!
0$
#80000000
1!
b00010000 #
1$
b00010000 &
b00010000 '
b10001000 (
1)
#90000000
0!
0$
#100000000
1!
b10001000 #
1$
b10001000 &
b10001000 '
b11000100 (
#105000000
#110000000
0!
0$
#120000000
1!
b11000100 #
1$
b11000100 &
b11000100 '
b11100010 (
#130000000
0!
0$
#140000000
1!
b11100010 #
1$
b11100010 &
b11100010 '
b01110001 (
0)
#150000000
0!
0$
#160000000
1!
b01110001 #
1$
b01110001 &
b01110001 '
b00111000 (
#170000000
0!
0$
#180000000
1!
b00111000 #
1$
b00111000 &
b00111000 '
b00011100 (
#190000000
0!
0$
#200000000
1!
b00011100 #
1$
b00011100 &
b00011100 '
b10001110 (
1)
#210000000
0!
0$
#220000000
1!
b10001110 #
1$
b10001110 &
b10001110 '
b01000111 (
0)
#230000000
0!
0$
#240000000
1!
b01000111 #
1$
b01000111 &
b01000111 '
b00100011 (
#250000000
0!
0$
#260000000
1!
b00100011 #
1$
b00100011 &
b00100011 '
b10010001 (
1)
#270000000
0!
0$
#280000000
1!
b10010001 #
1$
b10010001 &
b10010001 '
b01001000 (
0)
#290000000
0!
0$
#300000000
1!
b01001000 #
1$
b01001000 &
b01001000 '
b10100100 (
1)
#310000000
0!
0$
#320000000
1!
b10100100 #
1$
b10100100 &
b10100100 '
b11010010 (
#330000000
0!
0$
#340000000
1!
b11010010 #
1$
b11010010 &
b11010010 '
b11101001 (
#350000000
0!
0$
#360000000
1!
b11101001 #
1$
b11101001 &
b11101001 '
b01110100 (
0)
#370000000
0!
0$
#380000000
1!
b01110100 #
1$
b01110100 &
b01110100 '
b00111010 (
#390000000
0!
0$
#400000000
1!
b00111010 #
1$
b00111010 &
b00111010 '
b00011101 (
#410000000
0!
0$
#420000000
1!
b00011101 #
1$
b00011101 &
b00011101 '
b00001110 (
#430000000
0!
0$
#440000000
1!
b00001110 #
1$
b00001110 &
b00001110 '
b00000111 (
#450000000
0!
0$
#460000000
1!
b00000111 #
1$
b00000111 &
b00000111 '
b00000011 (
#470000000
0!
0$
#480000000
1!
b00000011 #
1$
b00000011 &
b00000011 '
b10000001 (
1)
#490000000
0!
0$
#500000000
1!
b10000001 #
1$
b10000001 &
b10000001 '
b11000000 (
