Digital_Systems/labs/experiments/projects/experiment4/16_1Mux/src/mux16_1.vhdl
library IEEE;
use IEEE.STD_LOGIC_1164.ALL;

entity mux16_1 is
	port(
	A : in STD_LOGIC_VECTOR(15 downto 0);
	S : in STD_LOGIC_VECTOR( 3 downto 0);
	Z1: out STD_LOGIC
);
end mux16_1;

architecture smsb of mux16_1 is
	component multiplexer_4_1
		port(
		A : in STD_LOGIC_VECTOR( 3 downto 0);
		S : in STD_LOGIC_VECTOR( 1 downto 0);
		Z : out STD_LOGIC
	);
	end component;

	signal temp: STD_LOGIC_VECTOR(3 downto 0);
begin
	m1: multiplexer_4_1 port map( A(3 downto 0), S(1 downto 0), temp(0));
	m2: multiplexer_4_1 port map( A(7 downto 4), S(1 downto 0), temp(1));
	m3: multiplexer_4_1 port map( A(11 downto 8), S(1 downto 0), temp(2));
	m4: multiplexer_4_1 port map( A(15 downto 12), S(1 downto 0), temp(3));
	m5: multiplexer_4_1 port map(temp, S(3 downto 2), Z1);
end smsb;

library IEEE;
use IEEE.STD_LOGIC_1164.ALL;

entity multiplexer_4_1 is
	port(
         A : in STD_LOGIC_VECTOR( 3 downto 0);
         S : in STD_LOGIC_VECTOR(1 downto 0);
         Z : out STD_LOGIC
         );
end multiplexer_4_1;

architecture multiplexer4_1_arc of multiplexer_4_1 is
begin
	with S select
		Z <= A(0) when "00",
		     A(1) when "01",
		     A(2) when "10",
		     A(3) when others;
end multiplexer4_1_arc;

Digital_Systems/labs/experiments/projects/experiment4/16_1Mux/testbench/tb_mux.vhdl
LIBRARY ieee;
USE ieee.std_logic_1164.ALL;

ENTITY tb_mux IS
END tb_mux;

ARCHITECTURE behavior OF tb_mux IS

    COMPONENT mux16_1
    PORT(
	A : in STD_LOGIC_VECTOR(15 downto 0);
	S: in STD_LOGIC_VECTOR(3 downto 0);
	Z1: out STD_LOGIC
        );
    END COMPONENT;

   signal A : std_logic_vector (15 downto 0) ;
   signal S : std_logic_vector (3 downto 0);
 	--Outputs
   signal Z1 : std_logic;

BEGIN
   uut: mux16_1 PORT MAP (
         A  => A,
         S => S,
         Z1 => Z1
        );

   stim_proc: process
   begin
      wait for 100 ns;
	A <= "1010101010101010";

	S <= "0000"; wait for 100 ns;
	S <= "0001"; wait for 100 ns;
	S <= "0010"; wait for 100 ns;
	S <= "0011"; wait for 100 ns;
	S <= "0100"; wait for 100 ns;
	S <= "0101"; wait for 100 ns;
	S <= "0110"; wait for 100 ns;
	S <= "0111"; wait for 100 ns;
	S <= "1000"; wait for 100 ns;
	S <= "1001"; wait for 100 ns;
	S <= "1010"; wait for 100 ns;
	S <= "1011"; wait for 100 ns;
	S <= "1100"; wait for 100 ns;
	S <= "1101"; wait for 100 ns;
	S <= "1110"; wait for 100 ns;
	S <= "1111"; wait for 100 ns;

	end process;
END;

Digital_Systems/labs/experiments/projects/experiment4/16_1Mux/simulation/tb_mux.vcd
$date
  Sat Sep 19 21:41:24 2020
$end
$version
  GHDL v0
$end
$timescale
  1 fs
$end
$scope module standard $end
$upscope $end
$scope module std_logic_1164 $end
$upscope $end
$scope module tb_mux $end
$var reg 16 ! a[15:0] $end
$var reg 4 " s[3:0] $end
$var reg 1 # z1 $end
$scope module uut $end
$var reg 16 $ a[15:0] $end
$var reg 4 % s[3:0] $end
$var reg 1 & z1 $end
$var reg 4 ' temp[3:0] $end
$scope module m1 $end
$var reg 4 ( a[3:0] $end
$var reg 2 ) s[1:0] $end
$var reg 1 * z $end
$upscope $end
$scope module m2 $end
$var reg 4 + a[3:0] $end
$var reg 2 , s[1:0] $end
$var reg 1 - z $end
$upscope $end
$scope module m3 $end
$var reg 4 . a[3:0] $end
$var reg 2 / s[1:0] $end
$var reg 1 0 z $end
$upscope $end
$scope module m4 $end
$var reg 4 1 a[3:0] $end
$var reg 2 2 s[1:0] $end
$var reg 1 3 z $end
$upscope $end
$scope module m5 $end
$var reg 4 4 a[3:0] $end
$var reg 2 5 s[1:0] $end
$var reg 1 6 z $end
$upscope $end
$upscope $end
$upscope $end
$enddefinitions $end
#0
bUUUUUUUUUUUUUUUU !
bUUUU "
U#
bUUUUUUUUUUUUUUUU $
bUUUU %
U&
bUUUU '
bUUUU (
bUU )
U*
bUUUU +
bUU ,
U-
bUUUU .
bUU /
U0
bUUUU 1
bUU 2
U3
bUUUU 4
bUU 5
U6
#100000000
b1010101010101010 !
b0000 "
0#
b1010101010101010 $
b0000 %
0&
b0000 '
b1010 (
b00 )
0*
b1010 +
b00 ,
0-
b1010 .
b00 /
00
b1010 1
b00 2
03
b0000 4
b00 5
06
#200000000
b0001 "
1#
b0001 %
1&
b1111 '
b01 )
1*
b01 ,
1-
b01 /
10
b01 2
13
b1111 4
16
#300000000
b0010 "
0#
b0010 %
0&
b0000 '
b10 )
0*
b10 ,
0-
b10 /
00
b10 2
03
b0000 4
06
#400000000
b0011 "
1#
b0011 %
1&
b1111 '
b11 )
1*
b11 ,
1-
b11 /
10
b11 2
13
b1111 4
16
#500000000
b0100 "
0#
b0100 %
0&
b0000 '
b00 )
0*
b00 ,
0-
b00 /
00
b00 2
03
b0000 4
b01 5
06
#600000000
b0101 "
1#
b0101 %
1&
b1111 '
b01 )
1*
b01 ,
1-
b01 /
10
b01 2
13
b1111 4
16
#700000000
b0110 "
0#
b0110 %
0&
b0000 '
b10 )
0*
b10 ,
0-
b10 /
00
b10 2
03
b0000 4
06
#800000000
b0111 "
1#
b0111 %
1&
b1111 '
b11 )
1*
b11 ,
1-
b11 /
10
b11 2
13
b1111 4
16
#900000000
b1000 "
0#
b1000 %
0&
b0000 '
b00 )
0*
b00 ,
0-
b00 /
00
b00 2
03
b0000 4
b10 5
06
#1000000000
b1001 "
1#
b1001 %
1&
b1111 '
b01 )
1*
b01 ,
1-
b01 /
10
b01 2
13
b1111 4
16
#1100000000
b1010 "
0#
b1010 %
0&
b0000 '
b10 )
0*
b10 ,
0-
b10 /
00
b10 2
03
b0000 4
06
#1200000000
b1011 "
1#
b1011 %
1&
b1111 '
b11 )
1*
b11 ,
1-
b11 /
10
b11 2
13
b1111 4
16
#1300000000
b1100 "
0#
b1100 %
0&
b0000 '
b00 )
0*
b00 ,
0-
b00 /
00
b00 2
03
b0000 4
b11 5
06
#1400000000
b1101 "
1#
b1101 %
1&
b1111 '
b01 )
1*
b01 ,
1-
b01 /
10
b01 2
13
b1111 4
16
#1500000000
b1110 "
0#
b1110 %
0&
b0000 '
b10 )
0*
b10 ,
0-
b10 /
00
b10 2
03
b0000 4
06
#1600000000
b1111 "
1#
b1111 %
1&
b1111 '
b11 )
1*
b11 ,
1-
b11 /
10
b11 2
13
b1111 4
16
