Digital_Systems/labs/experiments/projects/experiment4/8_1Mux_or/src/mux8_1.vhdl
library IEEE;
use IEEE.STD_LOGIC_1164.ALL;

entity mux8_1 is
port(
	A : in STD_LOGIC_VECTOR(7 downto 0);
	S: in STD_LOGIC_VECTOR(1 downto 0);
	E:in STD_LOGIC;
	Z1: out STD_LOGIC
);
end mux8_1;

architecture smsb of mux8_1 is
component orgate
	port(
		A,B:in STD_LOGIC;
		Z: out STD_LOGIC
	);
	end component;

component multiplexer_4_1
	port(
		A : in STD_LOGIC_VECTOR(3 downto 0);
	        S : in STD_LOGIC_VECTOR(1 downto 0);
		E:in STD_LOGIC;
	Z: out STD_LOGIC);
	end component;
signal temp1, temp2,C: std_logic;
begin
	C<=not(E);
	m1: multiplexer_4_1 port map(A(3 downto 0),S,C,temp1);
	m2: multiplexer_4_1 port map(A(7 downto 4),S,E,temp2);
	m3: orgate port map(temp1,temp2,Z1);
end smsb;

library IEEE;
use IEEE.STD_LOGIC_1164.all;

entity multiplexer_4_1 is
port(
	A : in STD_LOGIC_VECTOR(3 downto 0);
	S : in STD_LOGIC_VECTOR(1 downto 0);
	E:in STD_LOGIC;
	Z : out STD_LOGIC
);
end multiplexer_4_1;

architecture multiplexer4_1_arc of multiplexer_4_1 is
begin
	with S select
	Z <= A(0) and E when "00" ,
	A(1) and E when "01" ,
	A(2) and E when "10" ,
	A(3) and E when others;
end multiplexer4_1_arc;


library IEEE;
use IEEE.STD_LOGIC_1164.ALL;

entity orgate is
port(
	A,B:in STD_LOGIC;
	Z:out STD_LOGIC
);
end orgate;

architecture sms of orgate is
begin
	Z<=A or B;
end sms;

Digital_Systems/labs/experiments/projects/experiment4/8_1Mux_or/testbench/tb_mux.vhdl
LIBRARY ieee;
USE ieee.std_logic_1164.ALL;

ENTITY tb_mux IS
END tb_mux;

ARCHITECTURE behavior OF tb_mux IS

    COMPONENT mux8_1
    PORT(
	A : in STD_LOGIC_VECTOR(7 downto 0);
	S: in STD_LOGIC_VECTOR(1 downto 0);
	E:in STD_LOGIC;
	Z1: out STD_LOGIC
        );
    END COMPONENT;

   signal A : std_logic_vector (7 downto 0) ;
   signal S : std_logic_vector (1 downto 0);
   signal E : std_logic;
 	--Outputs
   signal Z1 : std_logic;

BEGIN
   uut: mux8_1 PORT MAP (
         A  => A,
         S => S,
	 E => E,
         Z1 => Z1
        );

   stim_proc: process
   begin
      wait for 100 ns;
	A <= "10101010";
	E <= '0';

	S <= "00";
		wait for 100 ns;
	S <= "01";
		wait for 100 ns;
	S <= "10";
		wait for 100 ns;
	S <= "11";
		wait for 100 ns;
	E <= '1';
	S <= "00";
	        wait for 100 ns;
	S <= "01";
	        wait for 100 ns;
	S <= "10";
		wait for 100 ns;
	S <= "11";
		wait for 100 ns;
	end process;
END;

Digital_Systems/labs/experiments/projects/experiment4/8_1Mux_or/simulation/tb_mux.vcd
$date
  Sat Sep 19 20:25:12 2020
$end
$version
  GHDL v0
$end
$timescale
  1 fs
$end
$scope module standard $end
$upscope $end
$scope module std_logic_1164 $end
$upscope $end
$scope module tb_mux $end
$var reg 8 ! a[7:0] $end
$var reg 2 " s[1:0] $end
$var reg 1 # e $end
$var reg 1 $ z1 $end
$scope module uut $end
$var reg 8 % a[7:0] $end
$var reg 2 & s[1:0] $end
$var reg 1 ' e $end
$var reg 1 ( z1 $end
$var reg 1 ) temp1 $end
$var reg 1 * temp2 $end
$var reg 1 + c $end
$scope module m1 $end
$var reg 4 , a[3:0] $end
$var reg 2 - s[1:0] $end
$var reg 1 . e $end
$var reg 1 / z $end
$upscope $end
$scope module m2 $end
$var reg 4 0 a[3:0] $end
$var reg 2 1 s[1:0] $end
$var reg 1 2 e $end
$var reg 1 3 z $end
$upscope $end
$scope module m3 $end
$var reg 1 4 a $end
$var reg 1 5 b $end
$var reg 1 6 z $end
$upscope $end
$upscope $end
$upscope $end
$enddefinitions $end
#0
bUUUUUUUU !
bUU "
U#
U$
bUUUUUUUU %
bUU &
U'
U(
U)
U*
U+
bUUUU ,
bUU -
U.
U/
bUUUU 0
bUU 1
U2
U3
U4
U5
U6
#100000000
b10101010 !
b00 "
0#
0$
b10101010 %
b00 &
0'
0(
0)
0*
1+
b1010 ,
b00 -
1.
0/
b1010 0
b00 1
02
03
04
05
06
#200000000
b01 "
1$
b01 &
1(
1)
b01 -
1/
b01 1
14
16
#300000000
b10 "
0$
b10 &
0(
0)
b10 -
0/
b10 1
04
06
#400000000
b11 "
1$
b11 &
1(
1)
b11 -
1/
b11 1
14
16
#500000000
b00 "
1#
0$
b00 &
1'
0(
0)
0+
b00 -
0.
0/
b00 1
12
04
06
#600000000
b01 "
1$
b01 &
1(
1*
b01 -
b01 1
13
15
16
#700000000
b10 "
0$
b10 &
0(
0*
b10 -
b10 1
03
05
06
#800000000
b11 "
1$
b11 &
1(
1*
b11 -
b11 1
13
15
16
