Digital_Systems/labs/experiments/projects/experiment2/full_sub/basic_gates/src/subtractor.vhdl
library ieee;
use ieee.std_logic_1164.all;

entity full_subtractor is
    port (
        a  : in  std_logic;
        b  : in  std_logic;
        bi : in  std_logic;
        d  : out std_logic;
        bo : out std_logic);
end;

architecture SUB of full_subtractor is
begin
    d <= ((not a) and (not b) and bi) or (a and (not b) and (not bi)) or ((not
	 a) and b and (not bi)) or (a and b and bi);
    bo <= (b and bi) or ((not a) and b) or ((not a) and bi);
end;

Digital_Systems/labs/experiments/projects/experiment2/full_sub/basic_gates/testbench/sub_tb.vhdl
library ieee;
use ieee.std_logic_1164.all;

entity sub_tb is
end sub_tb;

architecture ADDER of sub_tb is
    component full_subtractor is
        port (
            a  : in  std_logic;
            b  : in  std_logic;
            bi : in  std_logic;
            d  : out std_logic;
            bo : out std_logic);
    end component;
    signal input  : std_logic_vector(2 downto 0);
    signal output : std_logic_vector(1 downto 0);
begin
    uut: full_subtractor port map (
        a => input(2),
        b => input(1),
        bi => input(0),
        d => output(0),
        bo => output(1)
    );

    stim_proc: process
    begin
        input <= "000"; wait for 10 ns; assert output = "00" report "0+0+0 failed";
        input <= "001"; wait for 10 ns; assert output = "11" report "0+0+1 failed";
        input <= "010"; wait for 10 ns; assert output = "11" report "0+1+0 failed";
        input <= "011"; wait for 10 ns; assert output = "10" report "0+1+1 failed";
        input <= "100"; wait for 10 ns; assert output = "01" report "1+0+0 failed";
        input <= "101"; wait for 10 ns; assert output = "00" report "1+0+1 failed";
        input <= "110"; wait for 10 ns; assert output = "00" report "1+1+0 failed";
        input <= "111"; wait for 10 ns; assert output = "11" report "1+1+1 failed";
        report "Full subtractor testbench finished";
        wait;
    end process;
end;

Digital_Systems/labs/experiments/projects/experiment2/full_sub/basic_gates/simulation/sub_tb.vcd
$date
  Sat Aug  8 20:55:29 2020
$end
$version
  GHDL v0
$end
$timescale
  1 fs
$end
$scope module standard $end
$upscope $end
$scope module std_logic_1164 $end
$upscope $end
$scope module sub_tb $end
$var reg 3 ! input[2:0] $end
$var reg 2 " output[1:0] $end
$scope module uut $end
$var reg 1 # a $end
$var reg 1 $ b $end
$var reg 1 % bi $end
$var reg 1 & d $end
$var reg 1 ' bo $end
$upscope $end
$upscope $end
$enddefinitions $end
#0
b000 !
b00 "
0#
0$
0%
0&
0'
#10000000
b001 !
b11 "
1%
1&
1'
#20000000
b010 !
1$
0%
#30000000
b011 !
b10 "
1%
0&
#40000000
b100 !
b01 "
1#
0$
0%
1&
0'
#50000000
b101 !
b00 "
1%
0&
#60000000
b110 !
1$
0%
#70000000
b111 !
b11 "
1%
1&
1'
