Digital_Systems/labs/experiments/projects/bhavesh/src/controller.vhdl
-- 4 way traffic light control

library ieee;
use ieee.std_logic_1164.all;
use ieee.numeric_std.all;

-- port definition
-- clr: clears all outputs
-- mode: '0' - auto, '1' - manual
-- switch: manual mode direction selector: E-W-N-S order
-- green, yellow, red: lights in 4 ways E-W-N-S order
-- zebraRed, zebraGreen: zebra crossing lights EW-NS order

entity controller is
    port(clr: in std_logic;
         clk: in std_logic;
         mode: in std_logic;
         switch: in std_logic_vector(3 downto 0);
         green: out std_logic_vector(3 downto 0);
         yellow: out std_logic_vector(3 downto 0);
         red: out std_logic_vector(3 downto 0);
         zebraRed: out std_logic_vector(1 downto 0);
         zebraGreen: out std_logic_vector(1 downto 0));
end controller;


architecture arch of controller is

    -- used in timer to generate delay
    constant longCount : integer := 30; --count 30 clock pulses
    constant shortCount : integer := 10; --count 10 clock pulses

    signal state: integer range 0 to 11;
    -- variable pre_status: integer := 0;
    signal timeout: std_logic := '0'; -- flag : '1' if timeout in any state
    signal Tl, Ts: std_logic := '0';  -- signals to trigger timer function : Tl - long time, Ts - short time

begin --architecture

    -- sequential circuit to determine present state
    seq: process (clr, mode, timeout, clk)
    begin
        if mode = '0' then
            if clr = '1' then
                state <= 0;
            elsif timeout = '1' and rising_edge(clk) then
                state <= (state + 1) mod 12;
            end if;

        -- manual mode
        elsif mode = '1' then
            -- save current state
            -- pre_state := state;

            if switch(3) = '1' then
                state <= 4;
            elsif switch(2) = '1' then
                state <= 2;
            elsif switch(1) = '1' then
                state <= 10;
            elsif switch(0) = '1' then
                state <= 8;
            end if;
        end if;
    end process;

    -- combinational circuit which maps present state to correspongind lights
    comb: process (state)
    begin
        Tl <= '0'; Ts <= '0';
        case state is
            when 0 =>
                -- EW green and Zebra NS GREEN, all others RED
                green(3 downto 2) <= "11"; red(3 downto 2) <= "00"; -- EW
                green(1 downto 0) <= "00"; red(1 downto 0) <= "11"; -- NS
                yellow(3 downto 0) <= "0000";

                zebraGreen(1) <= '0'; zebraRed(1) <= '1'; --EW
                zebraGreen(0) <= '1'; zebraRed(0) <= '0'; --NS

                -- start timer
                Tl <= '1';

            when 1 =>
                -- E - yellow, turn off green
                yellow(3) <= '1'; green(3) <= '0';

                -- start timer
                Ts <= '1';

            when 2 =>
                -- E-red, turn off yellow
                red(3) <= '1'; yellow(3) <= '0';
                --Zebra-NS red, turnoff green
                zebraRed(0) <= '1'; zebraGreen(0) <= '0';

                --start timer
                Tl <= '1';

            when 3 =>
                -- W-yellow, turn off green
                yellow(2) <= '1'; green(2) <= '0';

                --start timer
                Ts <= '1';

            when 4 =>
                -- W-red, turn off yellow
                red(2) <= '1'; yellow(2) <= '0';
                -- E-green, turn off red
                green(3) <= '1'; red(3) <= '0';

                --start timer
                Tl <= '1';

            when 5 =>
                -- E-yellow, turn off green
                yellow(3) <= '1'; green(3) <= '0';

                --start timer
                Ts <= '1';

            when 6 =>
                --E-red, turnoff yellow
                red(3) <= '1'; yellow(3) <= '0';
                --NS - green, turn off red
                green(1 downto 0) <= "11"; red(1 downto 0) <= "00";
                --Zebra-EW green, turn off red
                zebraGreen(1) <= '1'; zebraRed(1) <= '0';

                --start timer
                Tl <= '1';

            when 7 =>
                -- N-yellow, turnoff green
                yellow(1) <= '1'; green(1) <= '0';

                --start timer
                Ts <= '1';

            when 8 =>
                --N-red, turn off yellow
                red(1) <= '1'; yellow(1) <= '0';
                --Zebra EW- red, turnoff green
                zebraRed(1) <= '1'; zebraGreen(1) <= '0';

                --start timer
                Tl <= '1';

            when 9 =>
                --S-yellow, turnoff green
                yellow(0) <= '1'; green(0) <= '0';

                --start timer
                Ts <= '1';

            when 10 =>
                --S-red, turn off yellow
                red(0) <= '1'; yellow(0) <= '0';
                --N-green, turnoff red
                green(1) <= '1'; red(1) <= '1';

                --start timer
                Tl <= '1';

            when 11 =>
                --N-yellow, turn off green
                yellow(1) <= '1'; green(1) <= '0';

                --start timer
                Ts <= '1';

        end case;
    end process;

    -- timer process
    timer: process(Tl, Ts, clk)
    variable count : integer;
    begin
        timeout <= '0';
        count := 0;
        if Tl = '1' then
            for i in 1 to longCount loop
                if rising_edge(clk) and count <= longCount then
                    count := count + 1;
                end if;
        end loop;
		timeout <= '1';
        -- Tl <= '0';

        elsif Ts = '1' then
            -- timeout <= '0';
            -- count := 0;
            for i in 1 to shortCount loop
                if rising_edge(clk) and count <= shortCount then
                    count := count +1;
                end if;
        end loop;
		  timeout <= '1';
        -- Ts <= '0';

        end if;

    end process;

end arch ; -- arch

Digital_Systems/labs/experiments/projects/bhavesh/testbench/controller_tb.vhdl

LIBRARY ieee;
USE ieee.std_logic_1164.ALL;

-- Uncomment the following library declaration if using
-- arithmetic functions with Signed or Unsigned values

ENTITY controller_tb IS
END controller_tb;

ARCHITECTURE behavior OF controller_tb IS

    -- Component Declaration for the Unit Under Test (UUT)

    COMPONENT controller
    PORT(
         clr : IN  std_logic;
         clk : IN  std_logic;
         mode : IN  std_logic;
         switch : IN  std_logic_vector(3 downto 0);
         green : OUT  std_logic_vector(3 downto 0);
         yellow : OUT  std_logic_vector(3 downto 0);
         red : OUT  std_logic_vector(3 downto 0);
         zebraRed : OUT  std_logic_vector(1 downto 0);
         zebraGreen : OUT  std_logic_vector(1 downto 0)
        );
    END COMPONENT;


   --Inputs
   signal clr : std_logic := '0';
   signal clk : std_logic := '0';
   signal mode : std_logic := '0';
   signal switch : std_logic_vector(3 downto 0) := (others => '0');

 	--Outputs
   signal green : std_logic_vector(3 downto 0);
   signal yellow : std_logic_vector(3 downto 0);
   signal red : std_logic_vector(3 downto 0);
   signal zebraRed : std_logic_vector(1 downto 0);
   signal zebraGreen : std_logic_vector(1 downto 0);

   -- Clock period definitions
   constant clk_period : time := 10 ns;

BEGIN

	-- Instantiate the Unit Under Test (UUT)
   uut: controller PORT MAP (
          clr => clr,
          clk => clk,
          mode => mode,
          switch => switch,
          green => green,
          yellow => yellow,
          red => red,
          zebraRed => zebraRed,
          zebraGreen => zebraGreen
        );

   -- Clock process definitions
   clk_process :process
   begin
		clk <= '0';
		wait for clk_period/2;
		clk <= '1';
		wait for clk_period/2;
   end process;


   clear: process
	begin
		clr <= '1';
		wait for clk_period/2;
		clr <= '0';
		wait;
  end process;

  -- manual: process
  -- begin
  --   wait for clk_period * 5;
  --   mode <= '1';
  --   wait for clk_period;
  --   switch(3) <= '1';
  --   wait for clk_period * 5;
  --   switch(3) <= '0';
  --   wait for clk_period;
  --   mode <= '0';
  --   wait;
  -- end process;

END;

Digital_Systems/labs/experiments/projects/bhavesh/simulation/controller_tb.vcd
$date
  Sat Nov 28 17:48:11 2020
$end
$version
  GHDL v0
$end
$timescale
  1 fs
$end
$scope module standard $end
$upscope $end
$scope module std_logic_1164 $end
$upscope $end
$scope module numeric_std $end
$upscope $end
$scope module controller_tb $end
$var reg 1 ! clr $end
$var reg 1 " clk $end
$var reg 1 # mode $end
$var reg 4 $ switch[3:0] $end
$var reg 4 % green[3:0] $end
$var reg 4 & yellow[3:0] $end
$var reg 4 ' red[3:0] $end
$var reg 2 ( zebrared[1:0] $end
$var reg 2 ) zebragreen[1:0] $end
$scope module uut $end
$var reg 1 * clr $end
$var reg 1 + clk $end
$var reg 1 , mode $end
$var reg 4 - switch[3:0] $end
$var reg 4 . green[3:0] $end
$var reg 4 / yellow[3:0] $end
$var reg 4 0 red[3:0] $end
$var reg 2 1 zebrared[1:0] $end
$var reg 2 2 zebragreen[1:0] $end
$var integer 32 3 state $end
$var reg 1 4 timeout $end
$var reg 1 5 tl $end
$var reg 1 6 ts $end
$upscope $end
$upscope $end
$enddefinitions $end
#0
1!
0"
0#
b0000 $
b1100 %
b0000 &
b0011 '
b10 (
b01 )
1*
0+
0,
b0000 -
b1100 .
b0000 /
b0011 0
b10 1
b01 2
b0 3
14
15
06
#5000000
0!
1"
b0100 %
b1000 &
0*
1+
b0100 .
b1000 /
b1 3
05
16
#10000000
0"
0+
#15000000
1"
b0000 &
b1011 '
b11 (
b00 )
1+
b0000 /
b1011 0
b11 1
b00 2
b10 3
15
06
#20000000
0"
0+
#25000000
1"
b0000 %
b0100 &
1+
b0000 .
b0100 /
b11 3
05
16
#30000000
0"
0+
#35000000
1"
b1000 %
b0000 &
b0111 '
1+
b1000 .
b0000 /
b0111 0
b100 3
15
06
#40000000
0"
0+
#45000000
1"
b0000 %
b1000 &
1+
b0000 .
b1000 /
b101 3
05
16
#50000000
0"
0+
#55000000
1"
b0011 %
b0000 &
b1100 '
b01 (
b10 )
1+
b0011 .
b0000 /
b1100 0
b01 1
b10 2
b110 3
15
06
#60000000
0"
0+
#65000000
1"
b0001 %
b0010 &
1+
b0001 .
b0010 /
b111 3
05
16
#70000000
0"
0+
#75000000
1"
b0000 &
b1110 '
b11 (
b00 )
1+
b0000 /
b1110 0
b11 1
b00 2
b1000 3
15
06
#80000000
0"
0+
#85000000
1"
b0000 %
b0001 &
1+
b0000 .
b0001 /
b1001 3
05
16
#90000000
0"
0+
#95000000
1"
b0010 %
b0000 &
b1111 '
1+
b0010 .
b0000 /
b1111 0
b1010 3
15
06
#100000000
0"
0+
#105000000
1"
b0000 %
b0010 &
1+
b0000 .
b0010 /
b1011 3
05
16
#110000000
0"
0+
#115000000
1"
b1100 %
b0000 &
b0011 '
b10 (
b01 )
1+
b1100 .
b0000 /
b0011 0
b10 1
b01 2
b0 3
15
06
#120000000
0"
0+
#125000000
1"
b0100 %
b1000 &
1+
b0100 .
b1000 /
b1 3
05
16
#130000000
0"
0+
#135000000
1"
b0000 &
b1011 '
b11 (
b00 )
1+
b0000 /
b1011 0
b11 1
b00 2
b10 3
15
06
#140000000
0"
0+
#145000000
1"
b0000 %
b0100 &
1+
b0000 .
b0100 /
b11 3
05
16
#150000000
0"
0+
#155000000
1"
b1000 %
b0000 &
b0111 '
1+
b1000 .
b0000 /
b0111 0
b100 3
15
06
#160000000
0"
0+
#165000000
1"
b0000 %
b1000 &
1+
b0000 .
b1000 /
b101 3
05
16
#170000000
0"
0+
#175000000
1"
b0011 %
b0000 &
b1100 '
b01 (
b10 )
1+
b0011 .
b0000 /
b1100 0
b01 1
b10 2
b110 3
15
06
#180000000
0"
0+
#185000000
1"
b0001 %
b0010 &
1+
b0001 .
b0010 /
b111 3
05
16
#190000000
0"
0+
#195000000
1"
b0000 &
b1110 '
b11 (
b00 )
1+
b0000 /
b1110 0
b11 1
b00 2
b1000 3
15
06
#200000000
0"
0+
#205000000
1"
b0000 %
b0001 &
1+
b0000 .
b0001 /
b1001 3
05
16
#210000000
0"
0+
#215000000
1"
b0010 %
b0000 &
b1111 '
1+
b0010 .
b0000 /
b1111 0
b1010 3
15
06
#220000000
0"
0+
#225000000
1"
b0000 %
b0010 &
1+
b0000 .
b0010 /
b1011 3
05
16
#230000000
0"
0+
#235000000
1"
b1100 %
b0000 &
b0011 '
b10 (
b01 )
1+
b1100 .
b0000 /
b0011 0
b10 1
b01 2
b0 3
15
06
#240000000
0"
0+
#245000000
1"
b0100 %
b1000 &
1+
b0100 .
b1000 /
b1 3
05
16
#250000000
0"
0+
#255000000
1"
b0000 &
b1011 '
b11 (
b00 )
1+
b0000 /
b1011 0
b11 1
b00 2
b10 3
15
06
#260000000
0"
0+
#265000000
1"
b0000 %
b0100 &
1+
b0000 .
b0100 /
b11 3
05
16
#270000000
0"
0+
#275000000
1"
b1000 %
b0000 &
b0111 '
1+
b1000 .
b0000 /
b0111 0
b100 3
15
06
#280000000
0"
0+
#285000000
1"
b0000 %
b1000 &
1+
b0000 .
b1000 /
b101 3
05
16
#290000000
0"
0+
#295000000
1"
b0011 %
b0000 &
b1100 '
b01 (
b10 )
1+
b0011 .
b0000 /
b1100 0
b01 1
b10 2
b110 3
15
06
#300000000
0"
0+
#305000000
1"
b0001 %
b0010 &
1+
b0001 .
b0010 /
b111 3
05
16
#310000000
0"
0+
#315000000
1"
b0000 &
b1110 '
b11 (
b00 )
1+
b0000 /
b1110 0
b11 1
b00 2
b1000 3
15
06
#320000000
0"
0+
#325000000
1"
b0000 %
b0001 &
1+
b0000 .
b0001 /
b1001 3
05
16
#330000000
0"
0+
#335000000
1"
b0010 %
b0000 &
b1111 '
1+
b0010 .
b0000 /
b1111 0
b1010 3
15
06
#340000000
0"
0+
#345000000
1"
b0000 %
b0010 &
1+
b0000 .
b0010 /
b1011 3
05
16
#350000000
0"
0+
#355000000
1"
b1100 %
b0000 &
b0011 '
b10 (
b01 )
1+
b1100 .
b0000 /
b0011 0
b10 1
b01 2
b0 3
15
06
#360000000
0"
0+
#365000000
1"
b0100 %
b1000 &
1+
b0100 .
b1000 /
b1 3
05
16
#370000000
0"
0+
#375000000
1"
b0000 &
b1011 '
b11 (
b00 )
1+
b0000 /
b1011 0
b11 1
b00 2
b10 3
15
06
#380000000
0"
0+
#385000000
1"
b0000 %
b0100 &
1+
b0000 .
b0100 /
b11 3
05
16
#390000000
0"
0+
#395000000
1"
b1000 %
b0000 &
b0111 '
1+
b1000 .
b0000 /
b0111 0
b100 3
15
06
#400000000
0"
0+
#405000000
1"
b0000 %
b1000 &
1+
b0000 .
b1000 /
b101 3
05
16
#410000000
0"
0+
#415000000
1"
b0011 %
b0000 &
b1100 '
b01 (
b10 )
1+
b0011 .
b0000 /
b1100 0
b01 1
b10 2
b110 3
15
06
#420000000
0"
0+
#425000000
1"
b0001 %
b0010 &
1+
b0001 .
b0010 /
b111 3
05
16
#430000000
0"
0+
#435000000
1"
b0000 &
b1110 '
b11 (
b00 )
1+
b0000 /
b1110 0
b11 1
b00 2
b1000 3
15
06
#440000000
0"
0+
#445000000
1"
b0000 %
b0001 &
1+
b0000 .
b0001 /
b1001 3
05
16
#450000000
0"
0+
#455000000
1"
b0010 %
b0000 &
b1111 '
1+
b0010 .
b0000 /
b1111 0
b1010 3
15
06
#460000000
0"
0+
#465000000
1"
b0000 %
b0010 &
1+
b0000 .
b0010 /
b1011 3
05
16
#470000000
0"
0+
#475000000
1"
b1100 %
b0000 &
b0011 '
b10 (
b01 )
1+
b1100 .
b0000 /
b0011 0
b10 1
b01 2
b0 3
15
06
#480000000
0"
0+
#485000000
1"
b0100 %
b1000 &
1+
b0100 .
b1000 /
b1 3
05
16
#490000000
0"
0+
#495000000
1"
b0000 &
b1011 '
b11 (
b00 )
1+
b0000 /
b1011 0
b11 1
b00 2
b10 3
15
06
