Digital_Systems/labs/experiments/projects/experiment5/bcd_excess/behav/src/bcd2excess3.vhdl
library ieee;
use ieee.std_logic_1164.all;
use ieee.numeric_std.all;

entity bcd2excess3 is
port(bcd: in std_logic_vector (3 downto 0);
     e3: out std_logic_vector (3 downto 0));
end bcd2excess3;

architecture arch_bcd2excess3 of bcd2excess3 is

begin
  with bcd select
	  e3 <= "0011" WHEN "0000",
		"0100" when "0001",
		"0101" when "0010",
		"0110" when "0011",
		"0111" when "0100",
		"1000" when "0101",
		"1001" when "0110",
		"1010" when "0111",
		"1011" when "1000",
		"1100" when "1001",
		"1101" when "1010",
		"1110" when "1011",
		"1111" when "1100",
		"0000" when "1101",
		"0001" when "1110",
		"0010" when others;
end arch_bcd2excess3;

Digital_Systems/labs/experiments/projects/experiment5/bcd_excess/behav/testbench/tb_bcd.vhdl
library ieee;
use ieee.std_logic_1164.all;

entity tb_bcd is
end tb_bcd;

architecture behav of tb_bcd is
	component bcd2excess3 is
		port(bcd: in std_logic_vector (3 downto 0);
		     e3 : inout std_logic_vector (3 downto 0)
	     );
	end component;

	signal input : std_logic_vector (3 downto 0);
	signal output: std_logic_vector (3 downto 0);
begin
	uut: bcd2excess3 port map(
		bcd => input,
		e3 => output);
	stim_proc: process
	begin
		input <= "0000"; wait for 100 ns;
		input <= "0001"; wait for 100 ns;
		input <= "0010"; wait for 100 ns;
		input <= "0011"; wait for 100 ns;
		input <= "0100"; wait for 100 ns;
		input <= "0101"; wait for 100 ns;
		input <= "0110"; wait for 100 ns;
		input <= "0111"; wait for 100 ns;
		input <= "1000"; wait for 100 ns;
		input <= "1001"; wait for 100 ns;
		input <= "1010"; wait for 100 ns;
		input <= "1011"; wait for 100 ns;
		input <= "1100"; wait for 100 ns;
		input <= "1101"; wait for 100 ns;
		input <= "1110"; wait for 100 ns;
		input <= "1111"; wait for 100 ns;
		wait;
	end process;
end;

Digital_Systems/labs/experiments/projects/experiment5/bcd_excess/behav/simulation/tb_bcd.vcd
$date
  Sun Sep 20 14:22:47 2020
$end
$version
  GHDL v0
$end
$timescale
  1 fs
$end
$scope module standard $end
$upscope $end
$scope module std_logic_1164 $end
$upscope $end
$scope module numeric_std $end
$upscope $end
$scope module tb_bcd $end
$var reg 4 ! input[3:0] $end
$var reg 4 " output[3:0] $end
$scope module uut $end
$var reg 4 # bcd[3:0] $end
$var reg 4 $ e3[3:0] $end
$upscope $end
$upscope $end
$enddefinitions $end
#0
b0000 !
b0011 "
b0000 #
b0011 $
#100000000
b0001 !
b0100 "
b0001 #
b0100 $
#200000000
b0010 !
b0101 "
b0010 #
b0101 $
#300000000
b0011 !
b0110 "
b0011 #
b0110 $
#400000000
b0100 !
b0111 "
b0100 #
b0111 $
#500000000
b0101 !
b1000 "
b0101 #
b1000 $
#600000000
b0110 !
b1001 "
b0110 #
b1001 $
#700000000
b0111 !
b1010 "
b0111 #
b1010 $
#800000000
b1000 !
b1011 "
b1000 #
b1011 $
#900000000
b1001 !
b1100 "
b1001 #
b1100 $
#1000000000
b1010 !
b1101 "
b1010 #
b1101 $
#1100000000
b1011 !
b1110 "
b1011 #
b1110 $
#1200000000
b1100 !
b1111 "
b1100 #
b1111 $
#1300000000
b1101 !
b0000 "
b1101 #
b0000 $
#1400000000
b1110 !
b0001 "
b1110 #
b0001 $
#1500000000
b1111 !
b0010 "
b1111 #
b0010 $
