Digital_Systems/labs/experiments/projects/experiment5/bcd_excess/dataflow/src/bcd2excess3.vhdl
library ieee;
use ieee.std_logic_1164.all;

entity bcd2excess3 is
port(bcd: in std_logic_vector (3 downto 0);
     e3: out std_logic_vector (3 downto 0));
end bcd2excess3;

architecture arch_bcd2excess3 of bcd2excess3 is
begin
	process(bcd)
	begin

	if (bcd < "1010") then
		e3(3) <= bcd(3) or (bcd(2) and (bcd(1) or bcd(0)) );
		e3(2) <= ( (not bcd(2)) and (bcd(1) or bcd(0)) ) or ( bcd(2) and
		(not bcd(1)) and (not bcd(0)) );
		e3(1) <= bcd(1) xnor bcd(0);
		e3(0) <= not bcd(0);
	else
		e3 <= "ZZZZ";
	end if;
	end process;
end arch_bcd2excess3;

Digital_Systems/labs/experiments/projects/experiment5/bcd_excess/behav/testbench/tb_bcd.vhdl
library ieee;
use ieee.std_logic_1164.all;

entity tb_bcd is
end tb_bcd;

architecture behav of tb_bcd is
	component bcd2excess3 is
		port(bcd: in std_logic_vector (3 downto 0);
		     e3 : inout std_logic_vector (3 downto 0)
	     );
	end component;

	signal input : std_logic_vector (3 downto 0);
	signal output: std_logic_vector (3 downto 0);
begin
	uut: bcd2excess3 port map(
		bcd => input,
		e3 => output);
	stim_proc: process
	begin
		input <= "0000"; wait for 100 ns;
		input <= "0001"; wait for 100 ns;
		input <= "0010"; wait for 100 ns;
		input <= "0011"; wait for 100 ns;
		input <= "0100"; wait for 100 ns;
		input <= "0101"; wait for 100 ns;
		input <= "0110"; wait for 100 ns;
		input <= "0111"; wait for 100 ns;
		input <= "1000"; wait for 100 ns;
		input <= "1001"; wait for 100 ns;
		input <= "1010"; wait for 100 ns;
		input <= "1011"; wait for 100 ns;
		input <= "1100"; wait for 100 ns;
		input <= "1101"; wait for 100 ns;
		input <= "1110"; wait for 100 ns;
		input <= "1111"; wait for 100 ns;
		wait;
	end process;
end;

Digital_Systems/labs/experiments/projects/experiment5/bcd_excess/dataflow/simulation/tb_bcd.vcd
$date
  Sun Sep 20 14:25:13 2020
$end
$version
  GHDL v0
$end
$timescale
  1 fs
$end
$scope module standard $end
$upscope $end
$scope module std_logic_1164 $end
$upscope $end
$scope module tb_bcd $end
$var reg 4 ! input[3:0] $end
$var reg 4 " output[3:0] $end
$scope module uut $end
$var reg 4 # bcd[3:0] $end
$var reg 4 $ e3[3:0] $end
$upscope $end
$upscope $end
$enddefinitions $end
#0
b0000 !
b0011 "
b0000 #
b0011 $
#100000000
b0001 !
b0100 "
b0001 #
b0100 $
#200000000
b0010 !
b0101 "
b0010 #
b0101 $
#300000000
b0011 !
b0110 "
b0011 #
b0110 $
#400000000
b0100 !
b0111 "
b0100 #
b0111 $
#500000000
b0101 !
b1000 "
b0101 #
b1000 $
#600000000
b0110 !
b1001 "
b0110 #
b1001 $
#700000000
b0111 !
b1010 "
b0111 #
b1010 $
#800000000
b1000 !
b1011 "
b1000 #
b1011 $
#900000000
b1001 !
b1100 "
b1001 #
b1100 $
#1000000000
b1010 !
bZZZZ "
b1010 #
bZZZZ $
#1100000000
b1011 !
b1011 #
#1200000000
b1100 !
b1100 #
#1300000000
b1101 !
b1101 #
#1400000000
b1110 !
b1110 #
#1500000000
b1111 !
b1111 #
