Digital_Systems/labs/experiments/projects/basic_gates/src/adder.vhdl
library ieee;
use ieee.std_logic_1164.all;

entity full_adder is
    port (
        a  : in  std_logic;
        b  : in  std_logic;
        c  : in  std_logic;
        co : out std_logic);
end;

architecture ADDER of full_adder is
begin
    co <= (a and b) or (not a and c);
end;

Digital_Systems/labs/experiments/projects/basic_gates/testbench/adder_tb.vhdl
library ieee;
use ieee.std_logic_1164.all;

entity adder_tb is
end adder_tb;

architecture ADDER of adder_tb is
    component full_adder is
        port (
            a  : in  std_logic;
            b  : in  std_logic;
            c : in  std_logic;
            co : out std_logic);
    end component;
    signal input  : std_logic_vector(2 downto 0);
    signal output : std_logic;
begin
    uut: full_adder port map (
        c => input(2),
        b => input(1),
        a => input(0),
        co => output
    );

    stim_proc: process
    begin
        input <= "000"; wait for 10 ns;
        input <= "001"; wait for 10 ns;
        input <= "010"; wait for 10 ns;
        input <= "011"; wait for 10 ns;
        input <= "100"; wait for 10 ns;
        input <= "101"; wait for 10 ns;
        input <= "110"; wait for 10 ns;
        input <= "111"; wait for 10 ns;
        report "Full adder testbench finished";
        wait;
    end process;
end;

Digital_Systems/labs/experiments/projects/basic_gates/simulation/adder_tb.vcd
$date
  Thu Dec 17 14:41:23 2020
$end
$version
  GHDL v0
$end
$timescale
  1 fs
$end
$scope module standard $end
$upscope $end
$scope module std_logic_1164 $end
$upscope $end
$scope module adder_tb $end
$var reg 3 ! input[2:0] $end
$var reg 1 " output $end
$scope module uut $end
$var reg 1 # a $end
$var reg 1 $ b $end
$var reg 1 % c $end
$var reg 1 & co $end
$upscope $end
$upscope $end
$enddefinitions $end
#0
b000 !
0"
0#
0$
0%
0&
#10000000
b001 !
1#
#20000000
b010 !
0#
1$
#30000000
b011 !
1"
1#
1&
#40000000
b100 !
0#
0$
1%
#50000000
b101 !
0"
1#
0&
#60000000
b110 !
1"
0#
1$
1&
#70000000
b111 !
1#
