Digital_Systems/labs/experiments/projects/experiment4/full_sub/src/fullsubtractor.vhdl
library IEEE;
use IEEE.STD_LOGIC_1164.ALL;

entity fullsubtractor is
port(
A : in STD_LOGIC;
B: in STD_LOGIC;
C: in STD_LOGIC;
D:out STD_LOGIC;
BO: out STD_LOGIC
);
end fullsubtractor;

architecture smsb of fullsubtractor is
	component orgate
		port( A,B:in STD_LOGIC;
		Z : out STD_LOGIC);
	end component;

	component half_subtractor
		port( a: in STD_LOGIC;
		b: in STD_LOGIC;
		diff : out STD_LOGIC;
		borrow: out STD_LOGIC);
	end component;

	signal sum1,carry1,carry2: std_logic;
	begin
	m1: half_subtractor port map(A,B,sum1,carry1);
	m2: half_subtractor port map(C,sum1,D,carry2);
	m3: half_subtractor port map(carry1, carry2, BO);
end smsb;

library IEEE;
use IEEE.STD_LOGIC_1164.ALL;

entity half_subtractor is
   port(a,b:in STD_LOGIC; diff,borrow:out STD_LOGIC);
end half_subtractor;

architecture halfsubtractor of half_subtractor is
begin
	diff <= a xor b;
	borrow <= not(a) and b;
end halfsubtractor;

Digital_Systems/labs/experiments/projects/experiment4/full_sub/testbench/sub_tb.vhdl
library ieee;
use ieee.std_logic_1164.all;

entity sub_tb is
end sub_tb;

architecture ADDER of sub_tb is
    component fullsubtractor is
        port (
            A  : in  std_logic;
            B  : in  std_logic;
            C : in  std_logic;
            D  : out std_logic;
            BO : out std_logic);
    end component;
    signal input  : std_logic_vector(2 downto 0);
    signal output : std_logic_vector(1 downto 0);
begin
    uut: fullsubtractor port map (
        A => input(2),
        B => input(1),
        C => input(0),
        D => output(0),
        BO => output(1)
    );

    stim_proc: process
    begin
        input <= "000"; wait for 10 ns; assert output = "00" report "0+0+0 failed";
        input <= "001"; wait for 10 ns; assert output = "11" report "0+0+1 failed";
        input <= "010"; wait for 10 ns; assert output = "11" report "0+1+0 failed";
        input <= "011"; wait for 10 ns; assert output = "10" report "0+1+1 failed";
        input <= "100"; wait for 10 ns; assert output = "01" report "1+0+0 failed";
        input <= "101"; wait for 10 ns; assert output = "00" report "1+0+1 failed";
        input <= "110"; wait for 10 ns; assert output = "00" report "1+1+0 failed";
        input <= "111"; wait for 10 ns; assert output = "11" report "1+1+1 failed";
        report "Full subtractor testbench finished";
        wait;
    end process;
end;

Digital_Systems/labs/experiments/projects/experiment4/full_sub/simulation/sub_tb.vcd
$date
  Sat Sep 19 22:24:06 2020
$end
$version
  GHDL v0
$end
$timescale
  1 fs
$end
$scope module standard $end
$upscope $end
$scope module std_logic_1164 $end
$upscope $end
$scope module sub_tb $end
$var reg 3 ! input[2:0] $end
$var reg 2 " output[1:0] $end
$scope module uut $end
$var reg 1 # a $end
$var reg 1 $ b $end
$var reg 1 % c $end
$var reg 1 & d $end
$var reg 1 ' bo $end
$var reg 1 ( sum1 $end
$var reg 1 ) carry1 $end
$var reg 1 * carry2 $end
$scope module m1 $end
$var reg 1 + a $end
$var reg 1 , b $end
$var reg 1 - diff $end
$var reg 1 . borrow $end
$upscope $end
$scope module m2 $end
$var reg 1 / a $end
$var reg 1 0 b $end
$var reg 1 1 diff $end
$var reg 1 2 borrow $end
$upscope $end
$scope module m3 $end
$var reg 1 3 a $end
$var reg 1 4 b $end
$var reg 1 5 diff $end
$var reg 1 6 borrow $end
$upscope $end
$upscope $end
$upscope $end
$enddefinitions $end
#0
b000 !
b00 "
0#
0$
0%
0&
0'
0(
0)
0*
0+
0,
0-
0.
0/
00
01
02
03
04
05
06
#10000000
b001 !
b01 "
1%
1&
1/
11
#20000000
b010 !
b01 "
1$
0%
1&
0'
1(
1)
1*
1,
1-
1.
0/
10
11
12
13
14
05
#30000000
b011 !
b10 "
1%
0&
1'
0*
1/
01
02
04
15
#40000000
b100 !
b11 "
1#
0$
0%
1&
0)
1*
1+
0,
0.
0/
11
12
03
14
16
#50000000
b101 !
b00 "
1%
0&
0'
0*
1/
01
02
04
05
06
#60000000
b110 !
b00 "
1$
0%
0&
0'
0(
0*
1,
0-
0/
00
01
02
04
05
06
#70000000
b111 !
b01 "
1%
1&
1/
11
